fastapi_crudrouter_mongodb/__init__.py
fastapi_crudrouter_mongodb/core/__init__.py
fastapi_crudrouter_mongodb/core/models/CRUDEmbed.py
fastapi_crudrouter_mongodb/core/models/CRUDLookup.py
fastapi_crudrouter_mongodb/core/models/__init__.py
fastapi_crudrouter_mongodb/core/models/deleted_mongo_model.py
fastapi_crudrouter_mongodb/core/models/mongo_model.py
fastapi_crudrouter_mongodb/core/models/mongo_object_id_model.py
fastapi_crudrouter_mongodb/core/router/CRUDRouter.py
fastapi_crudrouter_mongodb/core/router/CRUDRouterFactory.py
fastapi_crudrouter_mongodb/core/router/CRUDRouterRepository.py
fastapi_crudrouter_mongodb/core/router/CRUDRouterService.py
fastapi_crudrouter_mongodb/core/router/__init__.py
fastapi_crudrouter_mongodb/core/router/embed/CRUDEmbedRouter.py
fastapi_crudrouter_mongodb/core/router/embed/CRUDEmbedRouterFactory.py
fastapi_crudrouter_mongodb/core/router/embed/CRUDEmbedRouterRepository.py
fastapi_crudrouter_mongodb/core/router/embed/__init__.py
fastapi_crudrouter_mongodb/core/router/lookup/CRUDLookupRouter.py
fastapi_crudrouter_mongodb/core/router/lookup/CRUDLookupRouterFactory.py
fastapi_crudrouter_mongodb/core/router/lookup/CRUDLookupRouterRepository.py
fastapi_crudrouter_mongodb/core/router/lookup/__init__.py
fastapi_crudrouter_mongodb/core/utils/__init__.py
fastapi_crudrouter_mongodb/core/utils/deprecated_util.py
fastapi_crudrouter_mongodb-0.1.4.dist-info/LICENSE
fastapi_crudrouter_mongodb-0.1.4.dist-info/METADATA
fastapi_crudrouter_mongodb-0.1.4.dist-info/WHEEL
fastapi_crudrouter_mongodb-0.1.4.dist-info/top_level.txt
fastapi_crudrouter_mongodb-0.1.4.dist-info/RECORD
